[
  {
    "id": "e7921186-08dc-474e-8ef5-ac0fe745a9c0",
    "name": "Gabriel Garcia Marquez",
    "nationality": "Colombian",
    "birthYear": 1927
  },
  {
    "id": "e7921186-08dc-474e-8ef5-ac0fe745a9c1",
    "name": "Jane Austen",
    "nationality": "British",
    "birthYear": 1775
  },
  {
    "id": "e7921186-08dc-474e-8ef5-ac0fe745a9c2",
    "name": "George Orwell",
    "nationality": "British",
    "birthYear": 1903
  },
  {
    "id": "e7921186-08dc-474e-8ef5-ac0fe745a9c3",
    "name": "J.R.R. Tolkien",
    "nationality": "British",
    "birthYear": 1892
  },
  {
    "id": "e7921186-08dc-474e-8ef5-ac0fe745a9c4",
    "name": "pepe",
    "nationality": "colombia",
    "birthYear": "1987"
  }
]